{
  "locked": false,
  "version": 2,
  "targets": {
    ".NETFramework,Version=v4.5.2": {
      "mongocsharpdriver/1.11.0": {
        "type": "package",
        "compile": {
          "lib/net35/MongoDB.Bson.dll": {},
          "lib/net35/MongoDB.Driver.dll": {}
        },
        "runtime": {
          "lib/net35/MongoDB.Bson.dll": {},
          "lib/net35/MongoDB.Driver.dll": {}
        }
      },
      "Newtonsoft.Json/8.0.3": {
        "type": "package",
        "compile": {
          "lib/net45/Newtonsoft.Json.dll": {}
        },
        "runtime": {
          "lib/net45/Newtonsoft.Json.dll": {}
        }
      },
      "RestSharp/105.2.3": {
        "type": "package",
        "compile": {
          "lib/net452/RestSharp.dll": {}
        },
        "runtime": {
          "lib/net452/RestSharp.dll": {}
        }
      },
      "SharpRepository.CacheRepository/1.4.7": {
        "type": "package",
        "dependencies": {
          "SharpRepository.Repository": "1.4.7"
        },
        "compile": {
          "lib/net40/SharpRepository.CacheRepository.dll": {}
        },
        "runtime": {
          "lib/net40/SharpRepository.CacheRepository.dll": {}
        }
      },
      "SharpRepository.Caching.Redis/1.4.7": {
        "type": "package",
        "dependencies": {
          "Newtonsoft.Json": "6.0.5",
          "SharpRepository.Repository": "1.4.6",
          "StackExchange.Redis": "1.0.333"
        },
        "compile": {
          "lib/net45/SharpRepository.Caching.Redis.dll": {}
        },
        "runtime": {
          "lib/net45/SharpRepository.Caching.Redis.dll": {}
        }
      },
      "SharpRepository.MongoDbRepository/1.4.7": {
        "type": "package",
        "dependencies": {
          "SharpRepository.Repository": "1.4.7",
          "mongocsharpdriver": "1.11.0"
        },
        "compile": {
          "lib/net40/SharpRepository.MongoDbRepository.dll": {}
        },
        "runtime": {
          "lib/net40/SharpRepository.MongoDbRepository.dll": {}
        }
      },
      "SharpRepository.Repository/1.4.7": {
        "type": "package",
        "compile": {
          "lib/net40/SharpRepository.Repository.dll": {}
        },
        "runtime": {
          "lib/net40/SharpRepository.Repository.dll": {}
        }
      },
      "StackExchange.Redis/1.0.333": {
        "type": "package",
        "compile": {
          "lib/net45/StackExchange.Redis.dll": {}
        },
        "runtime": {
          "lib/net45/StackExchange.Redis.dll": {}
        }
      },
      "WebSocketSharp/1.0.3-rc10": {
        "type": "package",
        "compile": {
          "lib/websocket-sharp.dll": {}
        },
        "runtime": {
          "lib/websocket-sharp.dll": {}
        }
      }
    }
  },
  "libraries": {
    "mongocsharpdriver/1.11.0": {
      "sha512": "0FBUKnTd/WwVW8BhML7nL0+oNaDl1eieP5jDLolmSfb3Hk7x0ke4yMAapILWy8G+286T77QqzM2XpaPFaAAyRg==",
      "type": "package",
      "files": [
        "License.rtf",
        "lib/net35/MongoDB.Bson.XML",
        "lib/net35/MongoDB.Bson.dll",
        "lib/net35/MongoDB.Driver.XML",
        "lib/net35/MongoDB.Driver.dll",
        "mongocsharpdriver.1.11.0.nupkg.sha512",
        "mongocsharpdriver.nuspec"
      ]
    },
    "Newtonsoft.Json/8.0.3": {
      "sha512": "KGsYQdS2zLH+H8x2cZaSI7e+YZ4SFIbyy1YJQYl6GYBWjf5o4H1A68nxyq+WTyVSOJQ4GqS/DiPE+UseUizgMg==",
      "type": "package",
      "files": [
        "Newtonsoft.Json.8.0.3.nupkg.sha512",
        "Newtonsoft.Json.nuspec",
        "lib/net20/Newtonsoft.Json.dll",
        "lib/net20/Newtonsoft.Json.xml",
        "lib/net35/Newtonsoft.Json.dll",
        "lib/net35/Newtonsoft.Json.xml",
        "lib/net40/Newtonsoft.Json.dll",
        "lib/net40/Newtonsoft.Json.xml",
        "lib/net45/Newtonsoft.Json.dll",
        "lib/net45/Newtonsoft.Json.xml",
        "lib/portable-net40+sl5+wp80+win8+wpa81/Newtonsoft.Json.dll",
        "lib/portable-net40+sl5+wp80+win8+wpa81/Newtonsoft.Json.xml",
        "lib/portable-net45+wp80+win8+wpa81+dnxcore50/Newtonsoft.Json.dll",
        "lib/portable-net45+wp80+win8+wpa81+dnxcore50/Newtonsoft.Json.xml",
        "tools/install.ps1"
      ]
    },
    "RestSharp/105.2.3": {
      "sha512": "50LkciOclb7Lza9QXqR9reKeUoPlDQiFD4iBdOmd6twOBmTtqEFIOXQgdDdsTHQg4HcGh6EvrM6gN1X72vkJLA==",
      "type": "package",
      "files": [
        "RestSharp.105.2.3.nupkg.sha512",
        "RestSharp.nuspec",
        "lib/MonoAndroid10/RestSharp.dll",
        "lib/MonoAndroid10/RestSharp.xml",
        "lib/MonoTouch10/RestSharp.dll",
        "lib/MonoTouch10/RestSharp.xml",
        "lib/Xamarin.iOS10/RestSharp.dll",
        "lib/Xamarin.iOS10/RestSharp.xml",
        "lib/net35/RestSharp.dll",
        "lib/net35/RestSharp.xml",
        "lib/net4-client/RestSharp.dll",
        "lib/net4-client/RestSharp.xml",
        "lib/net4/RestSharp.dll",
        "lib/net4/RestSharp.xml",
        "lib/net45/RestSharp.dll",
        "lib/net45/RestSharp.xml",
        "lib/net451/RestSharp.dll",
        "lib/net451/RestSharp.xml",
        "lib/net452/RestSharp.dll",
        "lib/net452/RestSharp.xml",
        "lib/net46/RestSharp.dll",
        "lib/net46/RestSharp.xml",
        "lib/sl5/RestSharp.dll",
        "lib/sl5/RestSharp.xml",
        "lib/windowsphone8/RestSharp.dll",
        "lib/windowsphone8/RestSharp.xml",
        "lib/windowsphone81/RestSharp.dll",
        "lib/windowsphone81/RestSharp.xml",
        "readme.txt"
      ]
    },
    "SharpRepository.CacheRepository/1.4.7": {
      "sha512": "UOeJmbAwa2T3XV1twuSsTNG3UDfY6gL0/aUEY0TWIizqHjtJvhEVAmTkTrrdtwMo2dLT5h/Sg64ktBdYVCVscw==",
      "type": "package",
      "files": [
        "SharpRepository.CacheRepository.1.4.7.nupkg.sha512",
        "SharpRepository.CacheRepository.nuspec",
        "content/app.config.transform",
        "content/web.config.transform",
        "lib/net40/SharpRepository.CacheRepository.dll",
        "tools/Install.ps1"
      ]
    },
    "SharpRepository.Caching.Redis/1.4.7": {
      "sha512": "vnbVJA9lMvaRW+4H1ytuffWuGdjSBFoLxtiRDv8tIA+Pd4qD87iEf9tEsmCNGZeQ+sQBN1Sl1xV2B77Knyl9MA==",
      "type": "package",
      "files": [
        "SharpRepository.Caching.Redis.1.4.7.nupkg.sha512",
        "SharpRepository.Caching.Redis.nuspec",
        "content/app.config.transform",
        "content/web.config.transform",
        "lib/net45/SharpRepository.Caching.Redis.dll",
        "tools/Install.ps1"
      ]
    },
    "SharpRepository.MongoDbRepository/1.4.7": {
      "sha512": "qo5Wd4fJ2cf0fL65uj1LA4YDmVSLnayxNAO/KL2Cv1AdfFTSfyzLCTRlo9B+9Cs+bSH2etfY5lZiHpI59fEBKw==",
      "type": "package",
      "files": [
        "SharpRepository.MongoDbRepository.1.4.7.nupkg.sha512",
        "SharpRepository.MongoDbRepository.nuspec",
        "lib/net40/SharpRepository.MongoDbRepository.dll"
      ]
    },
    "SharpRepository.Repository/1.4.7": {
      "sha512": "TsuFLmZQso+cus8vkR08ukoHb/SkWdmxp7MFR6EIrJ6GRCKXBmw4SQomPiWZ08ZlPmgaKSdB5+mazln0Torzng==",
      "type": "package",
      "files": [
        "SharpRepository.Repository.1.4.7.nupkg.sha512",
        "SharpRepository.Repository.nuspec",
        "content/app.config.transform",
        "content/web.config.transform",
        "lib/net40/SharpRepository.Repository.dll",
        "tools/Install.ps1"
      ]
    },
    "StackExchange.Redis/1.0.333": {
      "sha512": "nljDzL6LVvzpYV7YPikIl/yd3pwTExT1ghpICEf2G5SsK/OrM8IVeGcsOE6U/0X0h+a9tdMlZ1qDEmcX1P1xkw==",
      "type": "package",
      "files": [
        "StackExchange.Redis.1.0.333.nupkg.sha512",
        "StackExchange.Redis.nuspec",
        "lib/net40/StackExchange.Redis.dll",
        "lib/net40/StackExchange.Redis.dll.config",
        "lib/net40/StackExchange.Redis.pdb",
        "lib/net40/StackExchange.Redis.xml",
        "lib/net45/StackExchange.Redis.dll",
        "lib/net45/StackExchange.Redis.pdb",
        "lib/net45/StackExchange.Redis.xml"
      ]
    },
    "WebSocketSharp/1.0.3-rc10": {
      "sha512": "DfB3JFsTfP/pajfSsMLe8MkLyRPieuLMbg79tASsgmbH28S3ZR2Zn70Vjsiq13yeTuLTFgQv/fDJ0pqMhvI7oQ==",
      "type": "package",
      "files": [
        "WebSocketSharp.1.0.3-rc10.nupkg.sha512",
        "WebSocketSharp.nuspec",
        "lib/websocket-sharp.dll",
        "lib/websocket-sharp.xml"
      ]
    }
  },
  "projectFileDependencyGroups": {
    "": [
      "Newtonsoft.Json >= 8.0.3",
      "RestSharp >= 105.2.3",
      "SharpRepository.CacheRepository >= 1.4.7",
      "SharpRepository.Caching.Redis >= 1.4.7",
      "SharpRepository.MongoDbRepository >= 1.4.7",
      "WebSocketSharp >= 1.0.3-rc10"
    ],
    ".NETFramework,Version=v4.5.2": []
  },
  "tools": {},
  "projectFileToolGroups": {}
}